frmplots/__init__.py
frmplots/cartogram.py
frmplots/cmap.py
frmplots/galaxyplot.py
frmplots/iplot.py
frmplots/norm.py
frmplots/platlabels.py
frmplots/plots.py
frmplots/plotstyle.py
frmplots/plotwheel.py
frmplots/qtable.py
frmplots-0.2.0.dist-info/METADATA
frmplots-0.2.0.dist-info/WHEEL
frmplots-0.2.0.dist-info/RECORD
